swisstopopy/__init__.py
swisstopopy/buildings.py
swisstopopy/dem.py
swisstopopy/settings.py
swisstopopy/stac.py
swisstopopy/tree_canopy.py
swisstopopy/utils.py
swisstopopy-0.1.0.dist-info/licenses/LICENSE
swisstopopy-0.1.0.dist-info/METADATA
swisstopopy-0.1.0.dist-info/WHEEL
swisstopopy-0.1.0.dist-info/top_level.txt
swisstopopy-0.1.0.dist-info/RECORD
