Metadata-Version: 2.4
Name: swisstopopy
Version: 0.1.0
Summary: swisstopo geospatial Python utilities
Author-email: Martí Bosch <marti.bosch@epfl.ch>
License-Expression: GPL-3.0-or-later
Project-URL: Repository, https://github.com/martibosch/swisstopopy
Classifier: Natural Language :: English
Classifier: Programming Language :: Python :: 3
Classifier: Programming Language :: Python :: 3.10
Classifier: Programming Language :: Python :: 3.11
Classifier: Programming Language :: Python :: 3.12
Classifier: Programming Language :: Python :: 3.13
License-File: LICENSE
Requires-Dist: geopandas>=1.0.0
Requires-Dist: numpy>=2.0.0
Requires-Dist: osmnx>=2.0.0
Requires-Dist: pooch
Requires-Dist: pyregeon
Requires-Dist: pystac-client
Requires-Dist: rasterio
Requires-Dist: rasterstats
Requires-Dist: shapely>=2.0.0
Requires-Dist: tqdm
Provides-Extra: dev
Requires-Dist: build; extra == "dev"
Requires-Dist: commitizen; extra == "dev"
Requires-Dist: pip; extra == "dev"
Requires-Dist: pre-commit; extra == "dev"
Requires-Dist: toml; extra == "dev"
Requires-Dist: tox; extra == "dev"
Requires-Dist: twine; extra == "dev"
Provides-Extra: doc
Requires-Dist: myst-parser; extra == "doc"
Requires-Dist: nbsphinx; extra == "doc"
Requires-Dist: pydata-sphinx-theme; extra == "doc"
Requires-Dist: setuptools; extra == "doc"
Requires-Dist: sphinx; extra == "doc"
Requires-Dist: sphinxemoji; extra == "doc"
Provides-Extra: pdal
Requires-Dist: pdal; extra == "pdal"
Provides-Extra: test
Requires-Dist: coverage[toml]; extra == "test"
Requires-Dist: pytest; extra == "test"
Requires-Dist: pytest-cov; extra == "test"
Requires-Dist: ruff; extra == "test"
Dynamic: license-file
